parampicker/__init__.py
parampicker/parampicker.py
parampicker-0.0.2.dist-info/LICENSE
parampicker-0.0.2.dist-info/METADATA
parampicker-0.0.2.dist-info/WHEEL
parampicker-0.0.2.dist-info/top_level.txt
parampicker-0.0.2.dist-info/RECORD
