Metadata-Version: 2.1
Name: parampicker
Version: 0.0.2
Summary: A package to select parameter settings using rank for grid searches in machine learning experiments
Home-page: https://github.com/khurramjaved96/experiment
Author: Khurram Javed
Author-email: khurramjaved1996@gmail.com
License: UNKNOWN
Platform: UNKNOWN
Classifier: Programming Language :: Python :: 3
Classifier: License :: OSI Approved :: MIT License
Classifier: Operating System :: OS Independent
Requires-Python: >=3.5
